<?xml version="1.0"?>
<exportedFiles>
  <exportedFile url="\Portal\SLXCustomerPortal\SupportFiles\jscript\Sage\MainView\Lead\nls\ImportLeadsWizard.js" timeStamp="2017-12-06T22:20:45.0000" />
  <exportedFile url="\Portal\SLXCustomerPortal\SupportFiles\jscript\Sage\MainView\Lead\nls\de\" />
  <exportedFile url="\Portal\SLXCustomerPortal\SupportFiles\jscript\Sage\MainView\Lead\nls\en\" />
  <exportedFile url="\Portal\SLXCustomerPortal\SupportFiles\jscript\Sage\MainView\Lead\nls\fr\" />
  <exportedFile url="\Portal\SLXCustomerPortal\SupportFiles\jscript\Sage\MainView\Lead\nls\it\" />
  <exportedFile url="\Portal\SLXCustomerPortal\SupportFiles\jscript\Sage\MainView\Lead\nls\ru\" />
  <exportedFile url="\Portal\SLXCustomerPortal\SupportFiles\jscript\Sage\MainView\Lead\nls\zh-cn\" />
  <exportedFile url="\Portal\SLXCustomerPortal\SupportFiles\jscript\Sage\MainView\Lead\nls\zh-tw\" />
</exportedFiles>