<?xml version="1.0"?>
<exportedFiles>
  <exportedFile url="\Portal\SlxClient\SupportFiles\jscript\Sage\Mingle\Widgets\infor.crm.opportunity\opportunity.common.ts" timeStamp="2017-12-06T22:16:44.0000" />
  <exportedFile url="\Portal\SlxClient\SupportFiles\jscript\Sage\Mingle\Widgets\infor.crm.opportunity\opportunity.controller.ts" timeStamp="2017-12-06T22:16:44.0000" />
  <exportedFile url="\Portal\SlxClient\SupportFiles\jscript\Sage\Mingle\Widgets\infor.crm.opportunity\opportunity.model.ts" timeStamp="2017-12-06T22:16:44.0000" />
  <exportedFile url="\Portal\SlxClient\SupportFiles\jscript\Sage\Mingle\Widgets\infor.crm.opportunity\opportunity.service.ts" timeStamp="2017-12-06T22:16:44.0000" />
  <exportedFile url="\Portal\SlxClient\SupportFiles\jscript\Sage\Mingle\Widgets\infor.crm.opportunity\opportunity-setting.controller.ts" timeStamp="2017-12-06T22:16:44.0000" />
  <exportedFile url="\Portal\SlxClient\SupportFiles\jscript\Sage\Mingle\Widgets\infor.crm.opportunity\settings.html" timeStamp="2017-12-06T22:16:44.0000" />
  <exportedFile url="\Portal\SlxClient\SupportFiles\jscript\Sage\Mingle\Widgets\infor.crm.opportunity\templateCache.ts" timeStamp="2017-12-06T22:16:44.0000" />
  <exportedFile url="\Portal\SlxClient\SupportFiles\jscript\Sage\Mingle\Widgets\infor.crm.opportunity\widget.html" timeStamp="2017-12-06T22:16:44.0000" />
  <exportedFile url="\Portal\SlxClient\SupportFiles\jscript\Sage\Mingle\Widgets\infor.crm.opportunity\widget.manifest" timeStamp="2017-12-06T22:16:44.0000" />
  <exportedFile url="\Portal\SlxClient\SupportFiles\jscript\Sage\Mingle\Widgets\infor.crm.opportunity\widget.ts" timeStamp="2017-12-06T22:16:44.0000" />
</exportedFiles>